seedfinder/__init__.py
seedfinder/cli.py
seedfinder/seedfinder.py
seedfinder/version.py
seedfinder-0.2.1.data/scripts/seedfinder
seedfinder-0.2.1.dist-info/LICENSE
seedfinder-0.2.1.dist-info/METADATA
seedfinder-0.2.1.dist-info/WHEEL
seedfinder-0.2.1.dist-info/top_level.txt
seedfinder-0.2.1.dist-info/RECORD
