Metadata-Version: 2.1
Name: seedfinder
Version: 0.2.1
Summary: Simple Python wrapper for seedfinder.eu's API
Home-page: https://github.com/hdb/seedfinder-python
Author: Hudson Bailey
Author-email: hudsondiggsbailey@gmail.com
License: MIT
Platform: UNKNOWN
Classifier: Programming Language :: Python :: 3
Classifier: Operating System :: OS Independent
Requires-Dist: requests
Requires-Dist: rich (>=12.3.0)
Requires-Dist: python-dotenv (>=0.18.0)
Requires-Dist: beautifulsoup4 (>=4.11.1)
